DRRTools/__init__.py
DRRTools/image_processing/__init__.py
DRRTools/image_processing/combination.py
DRRTools/image_processing/io.py
DRRTools/image_processing/plot.py
DRRTools/image_processing/transformation.py
DRRTools/image_processing/NLP/__init__.py
DRRTools/image_processing/NLP/tools.py
DRRTools-0.0.1.dist-info/LICENSE
DRRTools-0.0.1.dist-info/METADATA
DRRTools-0.0.1.dist-info/WHEEL
DRRTools-0.0.1.dist-info/top_level.txt
DRRTools-0.0.1.dist-info/RECORD
