Metadata-Version: 2.1
Name: DRRTools
Version: 0.0.1
Summary: My short description/Minha curta descrição
Home-page: https://github.com/DouglasRR/DRRTools
Author: Douglas R. Ramos
Author-email: douglaspro.business@gmail.com
Requires-Python: >=3.8
License-File: LICENSE
Requires-Dist: scikit-image
Requires-Dist: matplotlib
Requires-Dist: numpy
